adonitech/__init__.py
adonitech/sample_math_lib/operations.py
sample_math_lib-0.1.0.dist-info/licenses/LICENSE
sample_math_lib-0.1.0.dist-info/METADATA
sample_math_lib-0.1.0.dist-info/WHEEL
sample_math_lib-0.1.0.dist-info/top_level.txt
sample_math_lib-0.1.0.dist-info/RECORD
