Metadata-Version: 2.4
Name: sample-math-lib
Version: 0.1.0
Summary: Uma biblioteca de exemplo com operações matemáticas.
Author-email: Adonitech Solutions <contact@adonitech.com.br>
License: Proprietary
Project-URL: Homepage, https://github.com/adonitech-solutions/sample-python-lib
Project-URL: Bug Tracker, https://github.com/adonitech-solutions/sample-python-lib/issues
Classifier: Programming Language :: Python :: 3
Classifier: Operating System :: OS Independent
Requires-Python: >=3.7
License-File: LICENSE
Provides-Extra: test
Requires-Dist: pytest; extra == "test"
Dynamic: license-file
